[
    {
        "key": "dbln",
        "value": "%7B%2261576339350924%22%3A%22c4qnDO67%22%2C%2261584477128872%22%3A%22OkXV95my%22%7D",
        "domain": "facebook.com",
        "path": "/login/device-based/",
        "hostOnly": false,
        "creation": "2026-01-15T03:28:12.898Z",
        "lastAccessed": "2026-01-15T03:28:12.898Z"
    },
    {
        "key": "sb",
        "value": "vQ6XaH5QFaVCY5Zq3K3Ut_5g",
        "domain": "facebook.com",
        "path": "/",
        "hostOnly": false,
        "creation": "2026-01-15T03:28:12.898Z",
        "lastAccessed": "2026-01-15T03:28:12.898Z"
    },
    {
        "key": "datr",
        "value": "hbBnaeUoXgOLxIjgLIrFQKvd",
        "domain": "facebook.com",
        "path": "/",
        "hostOnly": false,
        "creation": "2026-01-15T03:28:12.898Z",
        "lastAccessed": "2026-01-15T03:28:12.898Z"
    },
    {
        "key": "locale",
        "value": "en_GB",
        "domain": "facebook.com",
        "path": "/",
        "hostOnly": false,
        "creation": "2026-01-15T03:28:12.898Z",
        "lastAccessed": "2026-01-15T03:28:12.898Z"
    },
    {
        "key": "c_user",
        "value": "61584477128872",
        "domain": "facebook.com",
        "path": "/",
        "hostOnly": false,
        "creation": "2026-01-15T03:28:12.898Z",
        "lastAccessed": "2026-01-15T03:28:12.898Z"
    },
    {
        "key": "xs",
        "value": "27%3AdyqjTHj41jmfcg%3A2%3A1768446424%3A-1%3A-1",
        "domain": "facebook.com",
        "path": "/",
        "hostOnly": false,
        "creation": "2026-01-15T03:28:12.898Z",
        "lastAccessed": "2026-01-15T03:28:12.898Z"
    },
    {
        "key": "pas",
        "value": "61578690950687%3AZ8QMvLJbwF%2C61579339285476%3A3OsIrrzv12%2C61579224127011%3AK6iWxZHwGz%2C61576339350924%3AMkoRcukCEz%2C61584477128872%3AtbXfgCbA6Q",
        "domain": "facebook.com",
        "path": "/",
        "hostOnly": false,
        "creation": "2026-01-15T03:28:12.898Z",
        "lastAccessed": "2026-01-15T03:28:12.898Z"
    },
    {
        "key": "vpd",
        "value": "v1%3B680x360x3",
        "domain": "facebook.com",
        "path": "/",
        "hostOnly": false,
        "creation": "2026-01-15T03:28:12.898Z",
        "lastAccessed": "2026-01-15T03:28:12.898Z"
    },
    {
        "key": "fr",
        "value": "0jucwcAnZXVnMaQoe.AWeH3yPWXZZU-_KQ--o--9Me2VreMSAOI0EwiR-Bl5L2MrV3XWw.BonlAF..AAA.0.0.BpaF6x.AWcVfSKgaza5cr2cxuBZ-wvTjPE",
        "domain": "facebook.com",
        "path": "/",
        "hostOnly": false,
        "creation": "2026-01-15T03:28:12.898Z",
        "lastAccessed": "2026-01-15T03:28:12.898Z"
    },
    {
        "key": "fbl_st",
        "value": "100720492%3BT%3A29474127",
        "domain": "facebook.com",
        "path": "/",
        "hostOnly": false,
        "creation": "2026-01-15T03:28:12.898Z",
        "lastAccessed": "2026-01-15T03:28:12.898Z"
    },
    {
        "key": "wl_cbv",
        "value": "v2%3Bclient_version%3A3051%3Btimestamp%3A1768447665",
        "domain": "facebook.com",
        "path": "/",
        "hostOnly": false,
        "creation": "2026-01-15T03:28:12.898Z",
        "lastAccessed": "2026-01-15T03:28:12.898Z"
    }
]
